Workbook

Sheet Read Me
B2: Bideo — Meta & Google App Ads Plan
B3: Goal: get REAL users (people who install AND keep watching / uploading), not just cheap installs.
B5: The one idea behind this plan
B6: 1. Ads only bring people to the app. The app must keep them — that's why Prerequisites come first.
B7: 2. Meta & Google find your customers FOR you, but only if you (a) track what real users do in the app and (b) tell the ads to find more of them.
B8: 3. Your ad content is your targeting: specific content in a specific language attracts the right people; generic ads attract random people.
B9: 4. Judge ads by cost per ACTIVATED user and day-7 retention — never by cost per install alone.
B11: Progress by phase
B12: Tab | C12: Tasks | D12: Done | E12: Must-do left | F12: % done | G12: What it covers
B13: 1. Prerequisites | C13: =COUNTA('1. Prerequisites'!A5:A35)-COUNTIF('1. Prerequisites'!A5:A35,"* *") -> 25 | D13: =COUNTIF('1. Prerequisites'!I5:I35,"Done")+COUNTIF('1. Prerequisites'!I5:I35,"Not needed") -> 0 | E13: =COUNTIFS('1. Prerequisites'!F5:F35,"Must",'1. Prerequisites'!I5:I35,"<>Done",'1. Prerequisites'!I5:I35,"<>Not needed") -> 16 | F13: =IF(C13>0,D13/C13,0) -> 0 | G13: Inside the app: stability, content, creators, onboarding, retention features, tracking SDKs, policy
B14: 2. Pre-Launch | C14: =COUNTA('2. Pre-Launch'!A5:A29)-COUNTIF('2. Pre-Launch'!A5:A29,"* *") -> 20 | D14: =COUNTIF('2. Pre-Launch'!I5:I29,"Done")+COUNTIF('2. Pre-Launch'!I5:I29,"Not needed") -> 0 | E14: =COUNTIFS('2. Pre-Launch'!F5:F29,"Must",'2. Pre-Launch'!I5:I29,"<>Done",'2. Pre-Launch'!I5:I29,"<>Not needed") -> 12 | F14: =IF(C14>0,D14/C14,0) -> 0 | G14: Strategy, ad accounts, tracking tests, store page, seed users, audiences, creatives
B15: 3. Launch | C15: =COUNTA('3. Launch'!A5:A20)-COUNTIF('3. Launch'!A5:A20,"* *") -> 12 | D15: =COUNTIF('3. Launch'!I5:I20,"Done")+COUNTIF('3. Launch'!I5:I20,"Not needed") -> 0 | E15: =COUNTIFS('3. Launch'!F5:F20,"Must",'3. Launch'!I5:I20,"<>Done",'3. Launch'!I5:I20,"<>Not needed") -> 8 | F15: =IF(C15>0,D15/C15,0) -> 0 | G15: Meta + Google campaign setup, first 7 days
B16: 4. Post-Launch | C16: =COUNTA('4. Post-Launch'!A5:A21)-COUNTIF('4. Post-Launch'!A5:A21,"* *") -> 13 | D16: =COUNTIF('4. Post-Launch'!I5:I21,"Done")+COUNTIF('4. Post-Launch'!I5:I21,"Not needed") -> 0 | E16: =COUNTIFS('4. Post-Launch'!F5:F21,"Must",'4. Post-Launch'!I5:I21,"<>Done",'4. Post-Launch'!I5:I21,"<>Not needed") -> 7 | F16: =IF(C16>0,D16/C16,0) -> 0 | G16: Weekly routine, scaling, re-engagement, feedback loop to the product
B17: Ready to launch ads? | C17: =IF(E13+E14=0,"YES — all Must items done","NOT YET — finish Must items in tabs 1 & 2") -> NOT YET — finish Must items in tabs 1 & 2
B19: Suggested timeline
B20: Weeks 1–3 | C20: Prerequisites (tab 1) — fix the app, fill content, onboard creators, add tracking
B21: Weeks 2–4 | C21: Pre-Launch (tab 2) — accounts, tracking test, store page, soft launch, creatives
B22: Week 5 | C22: Launch (tab 3) — small budgets, no edits for 7 days
B23: Week 6 onwards | C23: Post-Launch (tab 4) — weekly review with Decision Rules (tab 5) + KPI Tracker (tab 6)
B25: How to use this file
B26: • Yellow cells with blue text are for you to fill: Owner and Status in tabs 1–4, numbers in the KPI Tracker.
B27: • Status options: Not started / In progress / Done / Blocked / Not needed. This page updates automatically.
B28: • Priority: Must = don't launch without it · Should = do soon after · Nice = when you have time.
B29: • Every task has a 'Why' column — read it before skipping anything.
B31: Assumptions & notes
B32: • bideo.in shows only 'Watch. Create. Grow.' publicly, so this plan assumes: a free video app in India where creators upload and viewers watch; Android first.
B33: • All ₹ amounts and % targets are EXAMPLES to show the format — not industry benchmarks. Set your own after the first 2 weeks of real data.
B34: • Platform rules (Meta ~50 conversions/week to exit learning; lookalike seed min. 100 people; Google budget guidance) are as published by Meta/Google — check their help pages, as they change.

Sheet 1. Prerequisites
A1: 1. Prerequisites — what must be ready INSIDE the app before any ads
A2: Paid ads only bring people to the door. If the app can't keep them, every rupee is wasted. Finish all 'Must' items here before spending on ads.
A4: ID | B4: Area | C4: Task | D4: Why it matters (the reason) | E4: How to do it | F4: Priority | G4: Done when… | H4: Owner | I4: Status
A5: A. Stability & speed
A6: P01 | B6: Performance | C6: App is stable and crash-free | D6: People who arrive from an ad have zero loyalty. One crash = uninstall + 1-star review. Bad users also teach Meta/Google to find MORE people like them, so crashes poison your targeting. | E6: Add Firebase Crashlytics. Fix the top crashes. Test on 3–4 cheap Android phones (₹8–12k range) because that is what most Indian users have. | F6: Must | G6: Crash-free users ≥ 99% for 7 days in a row | I6: Not started
A7: P02 | B7: Performance | C7: Videos start fast, even on slow internet | D7: If a video buffers on first open, the user leaves before seeing any value — you paid for that install for nothing. Indian mobile networks vary a lot by city and time of day. | E7: Use adaptive streaming (HLS) so quality drops instead of buffering. Serve videos through a CDN with Indian servers. Show a thumbnail/preview instantly. Test on a 4G and a weak 3G connection. | F7: Must | G7: First video plays in under ~3 seconds on a mid-range phone on 4G | I7: Not started
A8: P03 | B8: Performance | C8: Small app size and fast first launch | D8: Big apps lose installs in the Play Store (users on low storage cancel). Every extra second on the splash screen loses users. | E8: Keep the APK/AAB small (use Android App Bundle). Remove heavy unused libraries. Measure cold start time. | F8: Should | G8: App opens to content in under ~2–3 seconds | I8: Not started
A9: B. Content & creators (supply side)
A10: P04 | B10: Content | C10: Enough content in your launch niche | D10: The ad promises a type of content (e.g. Tamil comedy). If a new viewer finds only 10 such videos, they finish them and never return — your ad money is wasted. | E10: Pick ONE launch niche (language + category). Fill it before ads: rough guide — enough videos that a new user can watch daily for a week without repeats (e.g. 200+ videos in that niche). | F10: Must | G10: A new user can scroll the niche for 30+ minutes without running out | I10: Not started
A11: P05 | B11: Creators | C11: A core group of active creators | D11: Viewers come back for NEW content. Without regular uploads the app feels dead by day 3, and retention (what makes ads profitable) collapses. | E11: Sign up 20–50 creators in the launch niche through direct outreach BEFORE viewer ads. Agree a posting rhythm (e.g. 3 videos/week each). | F11: Must | G11: New videos added in the niche every day for 2 weeks straight | I11: Not started
A12: P06 | B12: Creators | C12: Easy upload from phone | D12: Creators won't stay if uploading is painful. Fewer creators = less content = viewers leave. | E12: Upload from gallery, show progress, survive network drops (resumable upload), auto-compress, simple title/tags/language fields. | F12: Must | G12: A first-time creator uploads a video in under 2 minutes without help | I12: Not started
A13: P07 | B13: Creators | C13: Creator dashboard (views, followers, earnings) | D13: Creators stay where they can SEE growth. This is your main argument against YouTube/Instagram. | E13: Show views, watch time, followers and earnings (if any) per video. Update at least daily. | F13: Should | G13: Creators can see stats for each video inside the app | I13: Not started
A14: P08 | B14: Creators | C14: Creator profile share link | D14: Every creator who promotes their Bideo profile brings their fans for free. This lowers your cost per user on ads. | E14: Each creator gets a link/QR to their profile that opens the app (or Play Store, then the profile). | F14: Should | G14: Tapping a creator's link on WhatsApp opens their profile in the app | I14: Not started
A15: C. First-time user experience (onboarding)
A16: P09 | B16: Onboarding | C16: Let people watch before forcing login | D16: A login wall before any value is the #1 drop-off point for paid installs. You pay for the install, they quit at the OTP screen. | E16: Let new users watch 1–3 videos first. Ask to sign in only to like, follow, comment or upload. Offer phone OTP + Google one-tap. | F16: Must | G16: A new user is watching a video within 10 seconds of first open | I16: Not started
A17: P10 | B17: Onboarding | C17: Language & interest selection on first open | D17: If a Hindi speaker sees Malayalam videos first, they leave. The first screen must match what the ad promised. | E17: 1 screen: pick language(s); optional: pick 3 interests. Use it to build the first feed. Pre-select based on phone language. | F17: Must | G17: First feed matches the chosen language 100% | I17: Not started
A18: P11 | B18: Onboarding | C18: Deferred deep links (ad → exact video after install) | D18: If the ad shows a specific video, the user expects to see THAT video after install. Landing on a generic home screen breaks the promise and hurts activation. | E18: Use your attribution tool's deep linking (AppsFlyer OneLink / Branch). Note: Firebase Dynamic Links was shut down in Aug 2025 — do not build on it. | F18: Should | G18: Install from a test ad link opens the promoted video directly | I18: Not started
A19: P12 | B19: Experience | C19: Personalised feed that learns | D19: Users who quickly find content they like become regular users. A random feed leads to quick boredom. | E19: Start simple: rank by language + category + popularity, then add 'more like what you watched'. Even basic rules beat random. | F19: Should | G19: Feed changes after a user watches 5+ videos in one category | I19: Not started
A20: D. Retention & sharing features
A21: P13 | B21: Retention | C21: Push notifications (with permission prompt) | D21: Most new users forget the app within 1–2 days. Retention is what turns ad spend into real users. Android 13+ needs the user's permission to send notifications. | E21: Ask for permission at a good moment (after first video, not on launch). Send: new video from followed creator, trending in your language. Max 1–2 per day. | F21: Must | G21: Notification permission asked after first video; opt-in rate tracked | I21: Not started
A22: P14 | B22: Growth | C22: Share to WhatsApp / Instagram with a link back to the app | D22: Free sharing multiplies every paid install. In India, WhatsApp sharing is the biggest free growth channel. | E22: Share button on every video → WhatsApp first. The link opens the video in the app, or the Play Store if not installed. | F22: Must | G22: A shared link opens the right video for someone who has the app | I22: Not started
A23: P15 | B23: Growth | C23: Referral reward (invite friends) | D23: A referred user costs you nothing from ads and usually stays longer than a paid one. | E23: Simple reward: e.g. unlock a feature / badge / coins for inviting 3 friends who install and watch. Track referral source. | F23: Nice | G23: Referral installs are tracked separately from paid installs | I23: Not started
A24: P16 | B24: Retention | C24: Ask for a Play Store rating at a happy moment | D24: Store rating directly affects how many people install after clicking your ad (store conversion rate). | E24: Use the Google Play In-App Review API after e.g. the 10th video watched — never on first open, never after an error. | F24: Should | G24: Rating prompt live; store rating ≥ 4.0 | I24: Not started
A25: E. Tracking inside the app (SDKs & events)
A26: P17 | B26: Tracking | C26: Firebase / Google Analytics 4 SDK | D26: Google Ads App campaigns learn ONLY from events you send. No events = Google optimises for cheap, useless installs. | E26: Add Firebase SDK. Link Firebase to Google Ads. Verify events in Firebase DebugView. | F26: Must | G26: Events visible in Firebase DebugView from a test phone | I26: Not started
A27: P18 | B27: Tracking | C27: Meta (Facebook) SDK | D27: Same for Meta: without in-app events, Meta can only find 'people who install', not 'people who watch'. | E27: Add Meta SDK, register the app in Meta for Developers, check events in Events Manager → Test Events. | F27: Must | G27: Test events visible in Meta Events Manager | I27: Not started
A28: P19 | B28: Tracking | C28: Attribution tool (MMP: AppsFlyer / Adjust / Branch) | D28: Meta and Google each claim credit for the same install. An independent tool tells you the truth about which ad brought which user — and which source brings users who stay. | E28: Pick one (all have free/starter tiers). Add its SDK. Connect it to Meta and Google as an integrated partner. | F28: Should | G28: Test install from an ad link shows the correct source in the MMP | I28: Not started
A29: P20 | B29: Tracking | C29: Track the key in-app events | D29: These events are how you define a 'real customer'. You will tell the ad platforms to find more people who do THESE things. | E29: Minimum events: first_open, sign_up, video_start, video_complete, watched_3_videos (or 5 min watch time) = 'activated', follow_creator, share, video_uploaded (creators), day-2 return. | F29: Must | G29: All events fire correctly on a test phone with correct names | I29: Not started
A30: P21 | B30: Tracking | C30: Define ONE 'activated user' event | D30: You need one clear signal for 'this user got value'. Ads will be optimised for it. Too easy (app open) = junk users; too rare = not enough data for the algorithm. | E30: Recommended: 'watched 3+ videos within 24h of install'. Check that 20–40% of new users reach it — if far less, it is too hard for ads to learn from. | F30: Must | G30: Event exists and is marked as a conversion in Meta & Google | I30: Not started
A31: F. Policy & compliance (ads get rejected without these)
A32: P22 | B32: Policy | C32: Content moderation: report & block | D32: Google Play's user-generated-content policy requires a way to report content and block users. Meta/Google may reject ads or suspend the app if it hosts adult or pirated content. | E32: Report button on every video and profile; block user; a moderation queue; clear community guidelines in the app. | F32: Must | G32: Report + block working; moderation process defined | I32: Not started
A33: P23 | B33: Policy | C33: Copyright protection (especially movies) | D33: Pirated movies = takedown notices, Play Store removal and ad account bans. This can kill the whole business, not just the campaign. | E33: Creators must confirm they own the rights at upload. Fast takedown process. Never use copyrighted clips in your ads. | F33: Must | G33: Rights confirmation at upload + takedown contact published | I33: Not started
A34: P24 | B34: Policy | C34: Privacy policy, terms & account deletion | D34: Required by Google Play, Meta and Google Ads. Play also requires an in-app (and web) way to delete the account. India's DPDP Act also applies to personal data. | E34: Publish privacy policy and terms on bideo.in; link them in the app and stores. Add 'Delete account' in settings + a web form. | F34: Must | G34: Links live; deletion works; Play Data Safety form filled | I34: Not started
A35: P25 | B35: Policy | C35: iOS only: App Tracking Transparency prompt | D35: On iPhone, without the ATT prompt you can't track ad results properly. (Skip if Android-only at launch.) | E35: Add ATT prompt and SKAdNetwork setup via your MMP. | F35: Nice | G35: ATT prompt shows on iOS test device | I35: Not started

Sheet 2. Pre-Launch
A1: 2. Pre-Launch — strategy, tracking, store page, audiences, creatives
A2: Everything outside the app to prepare before turning ads on. Typical duration: 1–3 weeks.
A4: ID | B4: Area | C4: Task | D4: Why it matters (the reason) | E4: How to do it | F4: Priority | G4: Done when… | H4: Owner | I4: Status
A5: A. Strategy (decide before spending anything)
A6: B01 | B6: Strategy | C6: Pick ONE launch segment | D6: Small budgets spread across all of India get learned on nobody. One focused segment lets the algorithm find your people fast and makes your ads speak directly to them. | E6: Choose: 1 language + 1–2 content categories + the states where that language is spoken. Example: 'Tamil comedy & short films, Tamil Nadu, Android'. | F6: Must | G6: Segment written down and agreed | I6: Not started
A7: B02 | B7: Strategy | C7: Write the 'why Bideo' sentence | D7: Users already have YouTube, Instagram, MX Player. If you can't say why Bideo is different, the ad can't either and nobody installs. | E7: One sentence for viewers (e.g. 'Fresh Tamil short films every day, free') and one for creators (e.g. 'Get paid from your first 1,000 views'). | F7: Must | G7: Both sentences tested on 5 real people from the segment | I7: Not started
A8: B03 | B8: Strategy | C8: Set your budget and your maximum cost per real user | D8: Without a limit you can't decide which ads to stop. You need to know what a user is worth to you. | E8: Fix a test budget (e.g. ₹1,000–2,000/day per platform for 2–3 weeks). Estimate value per user (ad revenue or subscription) to set the max you can pay per activated user. | F8: Must | G8: Test budget + target cost per activated user filled in the KPI Tracker | I8: Not started
A9: B04 | B9: Strategy | C9: Agree success metrics before launch | D9: If you decide what 'good' means after seeing results, you will fool yourself. Install count alone looks good and means little. | E9: Main metric: cost per activated user. Supporting: D1 and D7 retention, creators uploading. See the 'Decision Rules' and 'KPI Tracker' tabs. | F9: Must | G9: Targets entered in KPI Tracker | I9: Not started
A10: B. Accounts & tracking setup
A11: B05 | B11: Accounts | C11: Meta Business Manager + ad account + app registered | D11: Needed to run app ads; verifying the business and domain reduces ad rejections and account bans. | E11: Create Business Manager, verify business, verify domain bideo.in, add payment method, register the app and link it to the ad account. | F11: Must | G11: Ad account active; app shows in Events Manager | I11: Not started
A12: B06 | B12: Accounts | C12: Google Ads account linked to Firebase / GA4 | D12: Google App campaigns need in-app conversions imported from Firebase to optimise for real users. | E12: Link Firebase project to Google Ads. Import first_open + your activated event as conversions. | F12: Must | G12: Activated event shows as a conversion in Google Ads | I12: Not started
A13: B07 | B13: Tracking | C13: End-to-end tracking test | D13: If tracking is broken, the algorithm learns from wrong data and you make decisions on wrong numbers. Most failed campaigns have a tracking problem. | E13: Fresh phone → click a test ad link → install → watch 3 videos. Confirm install + events appear in Meta, Google and the MMP with the right source. | F13: Must | G13: Test install correctly attributed on all 3 tools | I13: Not started
A14: B08 | B14: Tracking | C14: Pixel on bideo.in | D14: Lets you retarget website visitors and track people who click 'Download' on the site. | E14: Add Meta Pixel and Google tag to bideo.in. Track clicks on the Play Store / App Store buttons. | F14: Should | G14: Pixel events visible in Events Manager | I14: Not started
A15: B09 | B15: Safety | C15: Spending limits | D15: A mistake in budget settings can burn a month's money in a day. | E15: Set an account spending limit on Meta and a daily budget cap on Google. | F15: Must | G15: Limits set on both accounts | I15: Not started
A16: C. Store page (ASO) — where every paid click lands
A17: B10 | B17: Store | C17: Optimise the Play Store listing | D17: Every ad click lands here. If only 20% of visitors install instead of 40%, every install costs you 2× more. | E17: Clear title with keywords (e.g. 'Bideo: Watch & Create Videos'), short description with the 'why Bideo' line, 6–8 screenshots showing real content in the target language, a 30s preview video. | F17: Must | G17: Listing complete; store conversion rate tracked in Play Console | I17: Not started
A18: B11 | B18: Store | C18: Listing in the target language | D18: People install faster when the store page speaks their language. | E18: Add a localised listing (Play Console → Store listing → translations) for the launch language. | F18: Should | G18: Localised listing live | I18: Not started
A19: B12 | B19: Store | C19: Custom store listing for ad traffic | D19: Lets the store page match the ad exactly (e.g. Tamil ad → Tamil store page with Tamil screenshots). | E19: Play Console → Custom store listings; use a specific URL for ads. | F19: Nice | G19: Custom listing linked from ads | I19: Not started
A20: B13 | B20: Store | C20: Ratings and reviews before launch | D20: A new app with 0 or bad ratings converts poorly; ad traffic will check reviews. | E20: Get the first 30–50 genuine reviews from early users and creators (never fake/paid reviews — against Play policy). Reply to every review. | F20: Should | G20: Rating ≥ 4.0 with 30+ reviews | I20: Not started
A21: D. Seed users & audiences
A22: B14 | B22: Seeding | C22: Soft launch to get the first 300–1,000 real users | D22: Ad algorithms and lookalikes learn from your existing good users. Starting from zero data makes the first weeks expensive. It also tests the app with real people before you pay for traffic. | E22: Creators share their Bideo links, WhatsApp groups, college/community groups, friends & family in the target segment. | F22: Should | G22: 300+ installs and first retention numbers available | I22: Not started
A23: B15 | B23: Audiences | C23: Create the audience lists | D23: You need to (1) EXCLUDE existing users so you don't pay to reach them again and (2) build LOOKALIKES of your best users — the most reliable way to reach 'actual customers'. | E23: Meta custom audiences: all installers (to exclude), activated users (lookalike seed — Meta needs 100+ people from one country; 1,000+ works much better). | F23: Must | G23: Exclusion audience + seed audience created | I23: Not started
A24: E. Ad creatives
A25: B16 | B25: Creative | C25: Make 5–10 vertical video ads for viewers | D25: On Meta and Google today, the ad content IS the targeting: a Tamil comedy clip is only interesting to Tamil comedy fans, so the algorithm shows it to them. Generic ads attract random people. | E25: 9:16 vertical, 10–30s. Hook in the first 2 seconds. Real clips from the app. Target language + subtitles (most people watch muted). End: 'Free on Bideo — Install now'. | F25: Must | G25: At least 5 approved creatives ready | I25: Not started
A26: B17 | B26: Creative | C26: Test different hook types | D26: You can't know in advance what works. Testing different angles (not small colour changes) finds winners fast. | E26: Angle ideas: (1) best content teaser, (2) 'POV: you found an app full of ___', (3) creator talking to camera, (4) screen recording of the app, (5) trending/regional moment. | F26: Should | G26: At least 3 different angles in the first batch | I26: Not started
A27: B18 | B27: Creative | C27: Get written permission for clips used in ads | D27: Using a creator's video in an ad without permission = copyright complaint, ad rejection, and an angry creator. | E27: Simple consent from each creator whose content appears in ads (WhatsApp/email confirmation is better than nothing; a short agreement is best). | F27: Must | G27: Consent recorded for every clip used | I27: Not started
A28: B19 | B28: Creative | C28: Separate creatives for creators | D28: Creators and viewers want different things; one ad can't speak to both, so mixing them wastes money on both sides. | E28: Show earnings/growth: 'I posted my first video on Bideo and got ___ views'. Point to the creator sign-up flow. | F28: Should | G28: 2–3 creator ads ready | I28: Not started
A29: B20 | B29: Creative | C29: Static images & text for Google | D29: Google App campaigns build ads from the assets you give. Too few assets = weak, auto-generated ads. | E29: Prepare 5 headlines, 5 descriptions, several images (landscape, square, portrait), and videos in portrait + landscape. | F29: Should | G29: Full asset set uploaded | I29: Not started

Sheet 3. Launch
A1: 3. Launch — setting up and running the campaigns
A2: How to set up Meta and Google campaigns so they look for REAL users (people who watch), not just installs.
A4: ID | B4: Area | C4: Task | D4: Why it matters (the reason) | E4: How to do it | F4: Priority | G4: Done when… | H4: Owner | I4: Status
A5: A. Day-0 checks (just before turning ads on)
A6: L01 | B6: Checks | C6: Final tracking + app check | D6: Turning on ads with broken tracking or a crashing build is the most expensive mistake possible. | E6: Re-run the end-to-end test on the latest app version. Check Crashlytics. Confirm the Play Store build is the one with all SDKs. | F6: Must | G6: Test install + activation tracked today | I6: Not started
A7: L02 | B7: Checks | C7: Use a naming convention | D7: When you have 20 ads, clear names make the reports readable and decisions faster. | E7: Example: Platform_Goal_Segment_Creative_Date → META_ACT_TamilComedy_Hook1_Oct26. | F7: Should | G7: All campaigns/ads follow it | I7: Not started
A8: B. Meta (Facebook + Instagram)
A9: L03 | B9: Meta | C9: Campaign: App promotion → Advantage+ app campaign | D9: Meta's automated app campaign finds people itself using your creatives and conversion data. With small budgets this usually beats manual targeting. | E9: Objective: App promotion. Android app, country: India, the states for your language. Language setting: your launch language. Exclude your 'all installers' audience. | F9: Must | G9: Campaign live | I9: Not started
A10: L04 | B10: Meta | C10: Optimisation goal: the activated event (not just installs) | D10: 'Installs' gets you people who install anything for free. 'Activated' (watched 3+ videos) tells Meta to find people who actually watch. Meta needs ~50 such events per week to learn well. | E10: If you can afford ~50 activations/week → optimise for the activated event. If not, start with installs for 1–2 weeks, then switch once data builds up. | F10: Must | G10: Goal set as per the rule | I10: Not started
A11: L05 | B11: Meta | C11: Budget and structure | D11: Splitting a small budget across many campaigns starves each one; none of them exit the learning phase. | E11: 1 viewer campaign, 1 ad set, 3–6 creatives (e.g. ₹1,000–2,000/day). Creator campaign separate and smaller. | F11: Must | G11: Simple structure; budget set | I11: Not started
A12: L06 | B12: Meta | C12: Placements | D12: Reels and Stories fit vertical video. Audience Network (ads in other apps) often brings accidental clicks and low-quality installs. | E12: Start with Advantage+ placements, but check results by placement after week 1 and remove Audience Network if its users don't activate. | F12: Should | G12: Placement report reviewed on day 7 | I12: Not started
A13: L07 | B13: Meta | C13: Creator campaign (separate) | D13: Creators are a different audience with a different goal. Separate budget = separate learning. | E13: Small budget. Target interests like video editing, content creation, YouTube/Instagram creators + your language. Send to a creator sign-up page or lead form. | F13: Should | G13: Creator campaign live | I13: Not started
A14: C. Google (Play Store, YouTube, Search, Display)
A15: L08 | B15: Google | C15: App campaign for installs (Android) | D15: Google places your ad across Play Store search, YouTube, Search and Display — people searching for video apps are high-intent. | E15: Campaign type: App promotion → App installs. Location: India (or the target states). Language: your launch language + English. | F15: Must | G15: Campaign live | I15: Not started
A16: L09 | B16: Google | C16: Bidding: installs first, then in-app action | D16: Google also needs data to optimise for deeper events. Google suggests daily budget ≈ 50× target cost-per-install for install campaigns and ≈ 10× target cost-per-action for in-app action campaigns. | E16: Start with 'install volume' + 'in-app actions' tracking. Once you get ~10+ activated events/day, switch the goal to your activated event with a target cost per action. | F16: Must | G16: Bidding set; switch date planned | I16: Not started
A17: L10 | B17: Google | C17: Upload ALL asset types | D17: Google mixes assets into thousands of combinations. More good assets = more places your ad can show well. | E17: Headlines, descriptions, images in all ratios, YouTube videos in portrait + landscape. | F17: Should | G17: Asset strength shows 'Good' or 'Excellent' | I17: Not started
A18: D. First 7 days
A19: L11 | B19: Discipline | C19: Don't change campaigns during the learning phase | D19: Every big edit (budget, targeting, goal) restarts learning. Daily tweaking is how most beginners burn money. | E19: Only act on emergencies: ads rejected, tracking broken, spend far above plan, crashes. Otherwise wait 7 days. | F19: Must | G19: No edits in the first 7 days except emergencies | I19: Not started
A20: L12 | B20: Monitoring | C20: Daily 10-minute check | D20: Catch disasters early without over-managing. | E20: Check: spend vs plan, rejected ads, installs and activations arriving in all tools, crash rate, new store reviews. | F20: Must | G20: Checked daily | I20: Not started

Sheet 4. Post-Launch
A1: 4. Post-Launch — measure, optimise, scale
A2: What to do after ads are live: weekly routine, when to cut, when to scale, and how to feed learnings back into the app.
A4: ID | B4: Area | C4: Task | D4: Why it matters (the reason) | E4: How to do it | F4: Priority | G4: Done when… | H4: Owner | I4: Status
A5: A. Every week
A6: A01 | B6: Measure | C6: Fill the KPI Tracker | D6: Decisions must be based on cost per REAL user and retention, not on installs or clicks. | E6: Copy the numbers from Meta, Google and your MMP into the KPI Tracker tab every Monday. | F6: Must | G6: Tracker updated weekly | I6: Not started
A7: A02 | B7: Optimise | C7: Pause losing ads, keep winners | D7: Most ads fail; a few winners do the work. Moving money from losers to winners is the main way to lower your cost per user. | E7: Apply the 'Decision Rules' tab. Pause ads that spent 2× your target cost per activated user with no/poor activations. | F7: Must | G7: Weekly review done | I7: Not started
A8: A03 | B8: Optimise | C8: Check results by state, placement, device | D8: Some states or placements bring installs that never watch. Removing them cuts waste immediately. | E8: Meta: Breakdown → by region / placement. Google: report by network. Cut the worst if they're clearly worse after enough spend. | F8: Should | G8: Breakdowns reviewed | I8: Not started
A9: A04 | B9: Creative | C9: Add new creatives every 2–3 weeks | D9: People get tired of seeing the same ad (creative fatigue): CTR falls and costs rise. | E9: Watch frequency (> 3) and falling CTR. Make new versions of the winning angle + 1–2 new angles. | F9: Must | G9: 2–3 new creatives per fortnight | I9: Not started
A10: B. Scaling (when it works)
A11: A05 | B11: Scale | C11: Increase budget slowly | D11: Big budget jumps restart the learning phase and costs spike. | E11: Raise budget ~20% every 3–4 days while cost per activated user stays on target. | F11: Must | G11: Budget raised only on target | I11: Not started
A12: A06 | B12: Scale | C12: Switch to optimising for deeper events | D12: Once you have enough data, optimising for 'activated' or even 'returned on day 2' finds better users than installs. | E12: Meta: change goal to the activated event when you get ~50/week. Google: switch to in-app action bidding at ~10/day. | F12: Must | G12: Optimisation moved to the activated event | I12: Not started
A13: A07 | B13: Scale | C13: Build lookalikes from your BEST users | D13: Lookalikes of activated/retained users are the most reliable way to find people like your real customers. | E13: Upload activated users (1,000+ ideally) as a custom audience → 1% lookalike India / target states. Test it against broad. | F13: Should | G13: Lookalike test running | I13: Not started
A14: A08 | B14: Scale | C14: Expand to a 2nd language/niche only after the 1st works | D14: Expanding before the first segment is profitable doubles the waste instead of the growth. | E14: Repeat the full checklist (content → creators → creatives) for the new niche. | F14: Nice | G14: 1st segment on target for 4 weeks | I14: Not started
A15: C. Bring users back (re-engagement)
A16: A09 | B16: Retarget | C16: Re-engage installed-but-inactive users | D16: Bringing back a user you already paid for is cheaper than buying a new one. | E16: Push notifications + WhatsApp (with opt-in) + Google App engagement campaign / Meta retargeting of users inactive 7+ days with new content in their language. | F16: Should | G16: Re-engagement campaign or notification flow live | I16: Not started
A17: D. Learning loop with the product team
A18: A10 | B18: Product | C18: Find where users drop off and fix it in the app | D18: If users install but quit at login or after one video, more ad money won't help — the app must improve. Ads amplify a good product; they can't fix a weak one. | E18: Funnel in Firebase: install → first video → 3 videos → day-2 return. Find the biggest drop and fix that first. | F18: Must | G18: Biggest drop-off identified and fixed each month | I18: Not started
A19: A11 | B19: Product | C19: Compare retention by ad source | D19: Two sources with the same cost per install can bring users of very different quality. Day-7/day-30 retention reveals the truth. | E19: Use MMP cohort reports: D1/D7/D30 retention by platform, campaign and creative. | F19: Should | G19: Monthly cohort review | I19: Not started
A20: A12 | B20: Creators | C20: Grow creators continuously | D20: Viewer growth without new creators = content runs out = retention falls. | E20: Keep outreach going, feature top creators, creator referral bonuses, share success stories as ad creatives. | F20: Should | G20: Creator count rising monthly | I20: Not started
A21: A13 | B21: Review | C21: Monthly business review | D21: Decide whether to scale, hold or fix based on cost per real user vs value per user. | E21: Compare cost per activated user and D30 retention with value per user. Decide next month's budget. | F21: Must | G21: Decision recorded every month | I21: Not started

Sheet 5. Decision Rules
A1: 5. Decision Rules — what to do when you see this
A2: Use these every week with the KPI Tracker. 'Target' = the targets you set at the top of the KPI Tracker.
A4: Situation | B4: Signal (how you know) | C4: Action | D4: Why
A5: Ad is a clear loser | B5: Spent ≥ 2× target cost per activated user AND activations far below target | C5: Pause the ad. Keep the angle notes so you don't repeat it. | D5: Enough money has been spent to judge; more spend rarely turns a loser around.
A6: Ad is a winner | B6: Cost per activated user ≤ target for 7+ days | C6: Keep it on; make 2–3 new versions of the same angle; raise budget ~20% every 3–4 days. | D6: Winners are rare; variations of a winner are the safest new tests.
A7: Cheap installs, few activations | B7: Low cost per install but activation % far below your normal | C7: Check placement (Audience Network?), states, and ad promise vs app reality. Optimise for the activated event instead of installs. | D7: Cheap installs from the wrong people are the most common hidden waste.
A8: Many clicks, few installs | B8: Good CTR but low install rate (installs ÷ clicks) | C8: Fix the store page: screenshots, language, rating, preview video. Check the ad matches the store page. | D8: The ad works; the store page is losing the people you paid for.
A9: Few clicks | B9: CTR low vs your other ads | C9: Change the hook (first 2 seconds) and the content shown. Test a new angle, not a new colour. | D9: People aren't interested in what the ad shows.
A10: Ad fatigue | B10: Frequency > 3 and CTR falling week on week | C10: Add new creatives; retire the tired ones. | D10: The same people keep seeing the same ad and ignore it.
A11: Activations good, poor day-7 retention | B11: Activation % fine but D7 % below target | C11: Product problem: more fresh content, better notifications, better feed. Hold budget until it improves. | D11: Users like it at first but find no reason to return; more ads just buy more churn.
A12: Learning phase never ends | B12: Meta shows 'Learning limited' | C12: Merge ad sets, raise budget, or optimise for a more frequent event (e.g. installs or 1 video watched). | D12: The algorithm needs ~50 conversions/week per ad set to learn.
A13: Everything on target for 4 weeks | B13: Cost per activated user + D7 on target | C13: Scale budget gradually; test lookalikes; plan the 2nd language/niche. | D13: Proven economics — now growth is the goal.
A14: Tracking numbers don't match | B14: Meta/Google/MMP numbers differ a lot (> 20–30%) | C14: Trust the MMP for comparing sources; re-test tracking end to end. | D14: Each platform counts in its own favour; one neutral source keeps decisions honest.

Sheet 6. KPI Tracker
A1: 6. KPI Tracker — weekly numbers per platform
A2: Yellow cells with blue text = you type in. Grey/black cells = calculated automatically. Row 12 is an EXAMPLE — overwrite it with your first real week.
A4: Targets (set after your first 2 weeks)
A5: Target cost per activated user (₹) | D5: 60 | E5: Example values only — not benchmarks. Replace with your own numbers based on what a user is worth to you.
A6: Target activation % (activated ÷ installs) | D6: 0.3
A7: Target D1 retention % | D7: 0.3
A8: Target D7 retention % | D8: 0.12
A10: Inputs (type here) | L10: Calculated
A11: Week starting | B11: Platform | C11: Spend (₹) | D11: Impressions | E11: Clicks | F11: Installs | G11: Sign-ups | H11: Activated users | I11: Still active day 1 | J11: Still active day 7 | K11: Creators uploaded | L11: CTR | M11: Install rate (installs ÷ clicks) | N11: Cost per install (₹) | O11: Cost per sign-up (₹) | P11: Cost per ACTIVATED user (₹) | Q11: Activation % | R11: D1 retention % | S11: D7 retention % | T11: vs target
A12: 46328 | B12: Meta | C12: 10500 | D12: 210000 | E12: 3150 | F12: 630 | G12: 410 | H12: 180 | I12: 95 | J12: 40 | K12: 6 | L12: =IF(D12>0,E12/D12,"") -> 0.015 | M12: =IF(E12>0,F12/E12,"") -> 0.2 | N12: =IF(F12>0,C12/F12,"") -> 16.666667 | O12: =IF(G12>0,C12/G12,"") -> 25.609756 | P12: =IF(H12>0,C12/H12,"") -> 58.333333 | Q12: =IF(F12>0,H12/F12,"") -> 0.28571429 | R12: =IF(F12>0,I12/F12,"") -> 0.15079365 | S12: =IF(F12>0,J12/F12,"") -> 0.063492063 | T12: =IF(P12="","",IF(P12<=$D$5,"On target","Too expensive")) -> On target
L13: =IF(D13>0,E13/D13,"") | M13: =IF(E13>0,F13/E13,"") | N13: =IF(F13>0,C13/F13,"") | O13: =IF(G13>0,C13/G13,"") | P13: =IF(H13>0,C13/H13,"") | Q13: =IF(F13>0,H13/F13,"") | R13: =IF(F13>0,I13/F13,"") | S13: =IF(F13>0,J13/F13,"") | T13: =IF(P13="","",IF(P13<=$D$5,"On target","Too expensive"))
L14: =IF(D14>0,E14/D14,"") | M14: =IF(E14>0,F14/E14,"") | N14: =IF(F14>0,C14/F14,"") | O14: =IF(G14>0,C14/G14,"") | P14: =IF(H14>0,C14/H14,"") | Q14: =IF(F14>0,H14/F14,"") | R14: =IF(F14>0,I14/F14,"") | S14: =IF(F14>0,J14/F14,"") | T14: =IF(P14="","",IF(P14<=$D$5,"On target","Too expensive"))
L15: =IF(D15>0,E15/D15,"") | M15: =IF(E15>0,F15/E15,"") | N15: =IF(F15>0,C15/F15,"") | O15: =IF(G15>0,C15/G15,"") | P15: =IF(H15>0,C15/H15,"") | Q15: =IF(F15>0,H15/F15,"") | R15: =IF(F15>0,I15/F15,"") | S15: =IF(F15>0,J15/F15,"") | T15: =IF(P15="","",IF(P15<=$D$5,"On target","Too expensive"))
L16: =IF(D16>0,E16/D16,"") | M16: =IF(E16>0,F16/E16,"") | N16: =IF(F16>0,C16/F16,"") | O16: =IF(G16>0,C16/G16,"") | P16: =IF(H16>0,C16/H16,"") | Q16: =IF(F16>0,H16/F16,"") | R16: =IF(F16>0,I16/F16,"") | S16: =IF(F16>0,J16/F16,"") | T16: =IF(P16="","",IF(P16<=$D$5,"On target","Too expensive"))
L17: =IF(D17>0,E17/D17,"") | M17: =IF(E17>0,F17/E17,"") | N17: =IF(F17>0,C17/F17,"") | O17: =IF(G17>0,C17/G17,"") | P17: =IF(H17>0,C17/H17,"") | Q17: =IF(F17>0,H17/F17,"") | R17: =IF(F17>0,I17/F17,"") | S17: =IF(F17>0,J17/F17,"") | T17: =IF(P17="","",IF(P17<=$D$5,"On target","Too expensive"))
L18: =IF(D18>0,E18/D18,"") | M18: =IF(E18>0,F18/E18,"") | N18: =IF(F18>0,C18/F18,"") | O18: =IF(G18>0,C18/G18,"") | P18: =IF(H18>0,C18/H18,"") | Q18: =IF(F18>0,H18/F18,"") | R18: =IF(F18>0,I18/F18,"") | S18: =IF(F18>0,J18/F18,"") | T18: =IF(P18="","",IF(P18<=$D$5,"On target","Too expensive"))
L19: =IF(D19>0,E19/D19,"") | M19: =IF(E19>0,F19/E19,"") | N19: =IF(F19>0,C19/F19,"") | O19: =IF(G19>0,C19/G19,"") | P19: =IF(H19>0,C19/H19,"") | Q19: =IF(F19>0,H19/F19,"") | R19: =IF(F19>0,I19/F19,"") | S19: =IF(F19>0,J19/F19,"") | T19: =IF(P19="","",IF(P19<=$D$5,"On target","Too expensive"))
L20: =IF(D20>0,E20/D20,"") | M20: =IF(E20>0,F20/E20,"") | N20: =IF(F20>0,C20/F20,"") | O20: =IF(G20>0,C20/G20,"") | P20: =IF(H20>0,C20/H20,"") | Q20: =IF(F20>0,H20/F20,"") | R20: =IF(F20>0,I20/F20,"") | S20: =IF(F20>0,J20/F20,"") | T20: =IF(P20="","",IF(P20<=$D$5,"On target","Too expensive"))
L21: =IF(D21>0,E21/D21,"") | M21: =IF(E21>0,F21/E21,"") | N21: =IF(F21>0,C21/F21,"") | O21: =IF(G21>0,C21/G21,"") | P21: =IF(H21>0,C21/H21,"") | Q21: =IF(F21>0,H21/F21,"") | R21: =IF(F21>0,I21/F21,"") | S21: =IF(F21>0,J21/F21,"") | T21: =IF(P21="","",IF(P21<=$D$5,"On target","Too expensive"))
L22: =IF(D22>0,E22/D22,"") | M22: =IF(E22>0,F22/E22,"") | N22: =IF(F22>0,C22/F22,"") | O22: =IF(G22>0,C22/G22,"") | P22: =IF(H22>0,C22/H22,"") | Q22: =IF(F22>0,H22/F22,"") | R22: =IF(F22>0,I22/F22,"") | S22: =IF(F22>0,J22/F22,"") | T22: =IF(P22="","",IF(P22<=$D$5,"On target","Too expensive"))
L23: =IF(D23>0,E23/D23,"") | M23: =IF(E23>0,F23/E23,"") | N23: =IF(F23>0,C23/F23,"") | O23: =IF(G23>0,C23/G23,"") | P23: =IF(H23>0,C23/H23,"") | Q23: =IF(F23>0,H23/F23,"") | R23: =IF(F23>0,I23/F23,"") | S23: =IF(F23>0,J23/F23,"") | T23: =IF(P23="","",IF(P23<=$D$5,"On target","Too expensive"))
L24: =IF(D24>0,E24/D24,"") | M24: =IF(E24>0,F24/E24,"") | N24: =IF(F24>0,C24/F24,"") | O24: =IF(G24>0,C24/G24,"") | P24: =IF(H24>0,C24/H24,"") | Q24: =IF(F24>0,H24/F24,"") | R24: =IF(F24>0,I24/F24,"") | S24: =IF(F24>0,J24/F24,"") | T24: =IF(P24="","",IF(P24<=$D$5,"On target","Too expensive"))
... L51: =IF(D51>0,E51/D51,"") | M51: =IF(E51>0,F51/E51,"") | N51: =IF(F51>0,C51/F51,"") | O51: =IF(G51>0,C51/G51,"") | P51: =IF(H51>0,C51/H51,"") | Q51: =IF(F51>0,H51/F51,"") | R51: =IF(F51>0,I51/F51,"") | S51: =IF(F51>0,J51/F51,"") | T51: =IF(P51="","",IF(P51<=$D$5,"On target","Too expensive"))
A53: TOTAL (all rows) | C53: =SUM(C12:C51) -> 10500 | D53: =SUM(D12:D51) -> 210000 | E53: =SUM(E12:E51) -> 3150 | F53: =SUM(F12:F51) -> 630 | G53: =SUM(G12:G51) -> 410 | H53: =SUM(H12:H51) -> 180 | I53: =SUM(I12:I51) -> 95 | J53: =SUM(J12:J51) -> 40 | K53: =SUM(K12:K51) -> 6 | L53: =IF(D53>0,E53/D53,"") -> 0.015 | M53: =IF(E53>0,F53/E53,"") -> 0.2 | N53: =IF(F53>0,C53/F53,"") -> 16.666667 | O53: =IF(G53>0,C53/G53,"") -> 25.609756 | P53: =IF(H53>0,C53/H53,"") -> 58.333333 | Q53: =IF(F53>0,H53/F53,"") -> 0.28571429 | R53: =IF(F53>0,I53/F53,"") -> 0.15079365 | S53: =IF(F53>0,J53/F53,"") -> 0.063492063
A56: What each number means
A57: Activated user | D57: A new user who did your 'real customer' action (recommended: watched 3+ videos within 24h of install). Count it from Firebase / your MMP.
A58: Still active day 1 / day 7 | D58: Of this week's installs, how many opened the app again 1 day / 7 days after installing (from Firebase or MMP retention report).
A59: Cost per ACTIVATED user | D59: The most important number: Spend ÷ Activated users. What you actually pay for one real customer.
A60: CTR | D60: Clicks ÷ Impressions — is the ad interesting to the people seeing it?
A61: Install rate | D61: Installs ÷ Clicks — is the store page convincing people?
A62: Example row | D62: Row 12 shows invented example numbers to show the format. Replace them with your real week.
